ironic_python_agent/__init__.py
ironic_python_agent/agent.py
ironic_python_agent/burnin.py
ironic_python_agent/config.py
ironic_python_agent/device_hints.py
ironic_python_agent/disk_partitioner.py
ironic_python_agent/disk_utils.py
ironic_python_agent/dmi_inspector.py
ironic_python_agent/efi_utils.py
ironic_python_agent/encoding.py
ironic_python_agent/errors.py
ironic_python_agent/hardware.py
ironic_python_agent/inject_files.py
ironic_python_agent/inspect.py
ironic_python_agent/inspector.py
ironic_python_agent/ironic_api_client.py
ironic_python_agent/mdns.py
ironic_python_agent/netutils.py
ironic_python_agent/numa_inspector.py
ironic_python_agent/partition_utils.py
ironic_python_agent/qemu_img.py
ironic_python_agent/raid_utils.py
ironic_python_agent/tls_utils.py
ironic_python_agent/utils.py
ironic_python_agent/version.py
ironic_python_agent/api/__init__.py
ironic_python_agent/api/app.py
ironic_python_agent/api/request_log.py
ironic_python_agent/cmd/__init__.py
ironic_python_agent/cmd/agent.py
ironic_python_agent/cmd/inspect.py
ironic_python_agent/extensions/__init__.py
ironic_python_agent/extensions/base.py
ironic_python_agent/extensions/clean.py
ironic_python_agent/extensions/deploy.py
ironic_python_agent/extensions/flow.py
ironic_python_agent/extensions/image.py
ironic_python_agent/extensions/log.py
ironic_python_agent/extensions/poll.py
ironic_python_agent/extensions/rescue.py
ironic_python_agent/extensions/service.py
ironic_python_agent/extensions/standby.py
ironic_python_agent/extensions/system.py
ironic_python_agent/hardware_managers/__init__.py
ironic_python_agent/hardware_managers/cna.py
ironic_python_agent/hardware_managers/container.py
ironic_python_agent/hardware_managers/mlnx.py
ironic_python_agent/hardware_managers/nvidia/nvidia_fw_update.py
ironic_python_agent/metrics_lib/__init__.py
ironic_python_agent/metrics_lib/metrics.py
ironic_python_agent/metrics_lib/metrics_collector.py
ironic_python_agent/metrics_lib/metrics_statsd.py
ironic_python_agent-11.4.0.dist-info/licenses/AUTHORS
ironic_python_agent-11.4.0.dist-info/licenses/LICENSE
ironic_python_agent-11.4.0.dist-info/METADATA
ironic_python_agent-11.4.0.dist-info/WHEEL
ironic_python_agent-11.4.0.dist-info/entry_points.txt
ironic_python_agent-11.4.0.dist-info/pbr.json
ironic_python_agent-11.4.0.dist-info/top_level.txt
ironic_python_agent-11.4.0.dist-info/RECORD
