Metadata-Version: 2.4
Name: ironic-python-agent
Version: 11.4.0
Summary: Ironic Python Agent Ramdisk
Home-page: https://docs.openstack.org/ironic-python-agent/
Author: OpenStack
Author-email: openstack-discuss@lists.openstack.org
License: Apache-2
Classifier: Environment :: OpenStack
Classifier: Intended Audience :: System Administrators
Classifier: Intended Audience :: Information Technology
Classifier: License :: OSI Approved :: Apache Software License
Classifier: Operating System :: OS Independent
Classifier: Programming Language :: Python
Classifier: Programming Language :: Python :: Implementation :: CPython
Classifier: Programming Language :: Python :: 3 :: Only
Classifier: Programming Language :: Python :: 3
Classifier: Programming Language :: Python :: 3.10
Classifier: Programming Language :: Python :: 3.11
Classifier: Programming Language :: Python :: 3.12
Requires-Python: >=3.10
License-File: LICENSE
License-File: AUTHORS
Requires-Dist: pbr>=6.0.0
Requires-Dist: oslo.config>=9.7.1
Requires-Dist: oslo.concurrency>=7.1.0
Requires-Dist: oslo.log>=7.1.0
Requires-Dist: oslo.utils>=8.2.0
Requires-Dist: Pint>=0.5
Requires-Dist: psutil>=3.2.2
Requires-Dist: pyudev>=0.18
Requires-Dist: requests>=2.14.2
Requires-Dist: stevedore>=1.20.0
Requires-Dist: tenacity>=6.2.0
Requires-Dist: Werkzeug>=2.0.0
Requires-Dist: cryptography>=2.3
Requires-Dist: tooz>=2.7.2
Requires-Dist: zeroconf>=0.24.0
Requires-Dist: cheroot>=10.0.1
Provides-Extra: burnin-network-kazoo
Requires-Dist: kazoo>=2.8.0; extra == "burnin-network-kazoo"
Provides-Extra: test
Requires-Dist: coverage>=4.0; extra == "test"
Requires-Dist: testtools>=2.2.0; extra == "test"
Requires-Dist: oslotest>=3.2.0; extra == "test"
Requires-Dist: stestr>=1.0.0; extra == "test"
Requires-Dist: bandit<2.0.0,>=1.1.0; extra == "test"
Dynamic: author
Dynamic: author-email
Dynamic: classifier
Dynamic: description
Dynamic: home-page
Dynamic: license
Dynamic: license-file
Dynamic: provides-extra
Dynamic: requires-dist
Dynamic: requires-python
Dynamic: summary
